{
    "port": 3000,
    "password": "The password I have to remember",
    "cookieSecret": "My little secret",
    "sessionSecret": "My other secret",
    "adminAddress": "admin@example.net",
    "logAttackIpInCleartext": false,
    "trustProxy": false,
    "resources": [
        {
            "name": "My beloved server",
            "id": "beloved-server",
            "ip": "123.213.231.121",
            "hostname": "example.com",
            "mac": "12:ab:34:cd:56:ef",
            "location": "In the clouds",
            "actions": ["wake", "shutdown", "vpn-start", "vpn-stop"],
            "token": "<get this from your geminga remote node>"
        }
    ]
}